slon/__init__.py
slon-0.2.1.dist-info/LICENSE
slon-0.2.1.dist-info/METADATA
slon-0.2.1.dist-info/WHEEL
slon-0.2.1.dist-info/top_level.txt
slon-0.2.1.dist-info/RECORD
