Metadata-Version: 2.1
Name: slon
Version: 0.2.1
Summary: Simple Lightweight Object Notation
Home-page: https://github.com/gebrkn/slon
Author: Georg Barikin
Author-email: georg@merribithouse.net
License: MIT
Platform: UNKNOWN
